odoo/addons/sale_stock_weighing/README.rst
odoo/addons/sale_stock_weighing/__init__.py
odoo/addons/sale_stock_weighing/__manifest__.py
odoo/addons/sale_stock_weighing/i18n/sale_stock_weighing.pot
odoo/addons/sale_stock_weighing/models/__init__.py
odoo/addons/sale_stock_weighing/models/stock_move.py
odoo/addons/sale_stock_weighing/readme/CONTRIBUTORS.md
odoo/addons/sale_stock_weighing/readme/DESCRIPTION.md
odoo/addons/sale_stock_weighing/static/description/icon.png
odoo/addons/sale_stock_weighing/static/description/index.html
odoo/addons/sale_stock_weighing/views/stock_move_views.xml
odoo_addon_sale_stock_weighing-15.0.1.0.0.2.dist-info/METADATA
odoo_addon_sale_stock_weighing-15.0.1.0.0.2.dist-info/WHEEL
odoo_addon_sale_stock_weighing-15.0.1.0.0.2.dist-info/top_level.txt
odoo_addon_sale_stock_weighing-15.0.1.0.0.2.dist-info/RECORD
